postmansub/__init__.py
postmansub/main.py
postmansub-0.3.dist-info/METADATA
postmansub-0.3.dist-info/WHEEL
postmansub-0.3.dist-info/entry_points.txt
postmansub-0.3.dist-info/top_level.txt
postmansub-0.3.dist-info/RECORD
